Metadata-Version: 1.0
Name: pycws
Version: 0.2
Summary: A python api to cws
Home-page: http://github.com/javadogs/pycws
Author: Alexander Pilz
Author-email: info@syslab.com
License: APACHE 2.0
Platform: UNKNOWN
